qbox/__init__.py
qbox/__init__.pyi
qbox/_isinstance.py
qbox/_loop.py
qbox/py.typed
qbox/qbox.py
qbox/qbox.pyi
qbox-0.1.1.dist-info/METADATA
qbox-0.1.1.dist-info/WHEEL
qbox-0.1.1.dist-info/licenses/LICENSE.rst
qbox-0.1.1.dist-info/RECORD
