Metadata-Version: 2.4
Name: qbox
Version: 0.1.1
Summary: A lazily awaited container for async operations - Schrödinger's box for futures
Project-URL: Homepage, https://github.com/gtwohig/qbox
Project-URL: Documentation, https://qbox.readthedocs.io
Project-URL: Repository, https://github.com/gtwohig/qbox
Project-URL: Changelog, https://github.com/gtwohig/qbox/releases
Author: Greg Twohig
License-Expression: MIT
License-File: LICENSE.rst
Keywords: async,asyncio,concurrency,futures,lazy
Classifier: Development Status :: 3 - Alpha
Classifier: Framework :: AsyncIO
Classifier: Intended Audience :: Developers
Classifier: License :: OSI Approved :: MIT License
Classifier: Programming Language :: Python :: 3
Classifier: Programming Language :: Python :: 3.10
Classifier: Programming Language :: Python :: 3.11
Classifier: Programming Language :: Python :: 3.12
Classifier: Programming Language :: Python :: 3.13
Classifier: Programming Language :: Python :: 3.14
Classifier: Programming Language :: Python :: 3.15
Classifier: Programming Language :: Python :: Implementation :: CPython
Classifier: Programming Language :: Python :: Implementation :: PyPy
Classifier: Topic :: Software Development :: Libraries :: Python Modules
Classifier: Typing :: Typed
Requires-Python: >=3.10
